LICENSE
MANIFEST.in
README.md
requirements.txt
setup.py
win32printing.py
win32printing.egg-info/PKG-INFO
win32printing.egg-info/SOURCES.txt
win32printing.egg-info/dependency_links.txt
win32printing.egg-info/requires.txt
win32printing.egg-info/top_level.txt